README.md
setup.py
sqlite_uuid.py
uuid.c
sqlite_uuid.egg-info/PKG-INFO
sqlite_uuid.egg-info/SOURCES.txt
sqlite_uuid.egg-info/dependency_links.txt
sqlite_uuid.egg-info/top_level.txt