Metadata-Version: 2.1
Name: sqlite-uuid
Version: 0.9.1
Summary: Loadable uuid extension for sqlite
Home-page: https://github.com/litements/sqlite_uuid
Author: Ricardo Ander-Egg Aguilar
Author-email: rsubacc@gmail.com
License: UNKNOWN
Platform: UNKNOWN
Requires-Python: >=3.6
